pandstat/__init__.py
pandstat/dataframe_methods.py
pandstat/linear_models.py
pandstat-0.2.1.dist-info/LICENSE
pandstat-0.2.1.dist-info/METADATA
pandstat-0.2.1.dist-info/WHEEL
pandstat-0.2.1.dist-info/top_level.txt
pandstat-0.2.1.dist-info/RECORD
