Metadata-Version: 2.1
Name: pandstat
Version: 0.2.1
Summary: Package for easy statistical testing and useful dataframe methods in pandas!
Author-email: William Rosenbaum <william.rosenbaum88@gmail.com>
License: MIT License
Project-URL: Homepage, https://github.com/willros/pandstat
Keywords: pandas,tidyverse,statistics,dataframe-methods
Classifier: License :: OSI Approved :: MIT License
Classifier: Programming Language :: Python
Classifier: Programming Language :: Python :: 3
Requires-Python: >=3.7
License-File: LICENSE
Requires-Dist: altair
Requires-Dist: pandas
Requires-Dist: statsmodels
Requires-Dist: pandas-flavor
Provides-Extra: dev
Requires-Dist: black ; extra == 'dev'
Requires-Dist: pylint ; extra == 'dev'
